gym_multiagent/__init__.py
gym_multiagent/action.py
gym_multiagent/point.py
gym_multiagent/render.py
gym_multiagent/world.py
gym_multiagent/envs/__init__.py
gym_multiagent/envs/multiagent_env.py
gym_multiagent-1.0.0.dist-info/LICENSE
gym_multiagent-1.0.0.dist-info/METADATA
gym_multiagent-1.0.0.dist-info/WHEEL
gym_multiagent-1.0.0.dist-info/top_level.txt
gym_multiagent-1.0.0.dist-info/RECORD
